{
  "kind": "collectionType",
  "collectionName": "hero_banners",
  "info": {
    "singularName": "hero-banner",
    "pluralName": "hero-banners",
    "displayName": "hero-banners"
  },
  "options": {
    "draftAndPublish": true
  },
  "attributes": {
    "title": {
      "type": "string"
    },
    "description": {
      "type": "text"
    },
    "image": {
      "allowedTypes": [
        "images",
        "files",
        "videos",
        "audios"
      ],
      "type": "media",
      "multiple": true
    },
    "ButtonText": {
      "type": "string"
    },
    "ButtonLink": {
      "type": "string"
    }
  }
}
